LICENSE
MANIFEST.in
README.rst
VERSION
requirements.txt
setup.cfg
setup.py
src/fabutils/__init__.py
src/fabutils/api.py
src/fabutils/fs.py
src/fabutils/git.py
src/fabutils/lint.py
src/fabutils/util.py
src/fabutils/versioning.py
src/fabutils.egg-info/PKG-INFO
src/fabutils.egg-info/SOURCES.txt
src/fabutils.egg-info/dependency_links.txt
src/fabutils.egg-info/requires.txt
src/fabutils.egg-info/top_level.txt