Metadata-Version: 1.1
Name: fabutils
Version: 0.0.21
Summary: Various utilities to make writing fabfile easier.
Home-page: https://github.com/novopl/fabutils
Author: Mateusz 'novo' Klos
Author-email: novopl@gmail.com
License: MIT
Platform: UNKNOWN
Classifier: Development Status :: 3 - Alpha
Classifier: Topic :: Utilities
Classifier: Intended Audience :: Developers
Classifier: Programming Language :: Python
Classifier: License :: OSI Approved :: MIT License
